py_grpc_profile/__init__.py
py_grpc_profile/adapter/__init__.py
py_grpc_profile/adapter/cprofile_adapter.py
py_grpc_profile/adapter/interfaces.py
py_grpc_profile/aio/__init__.py
py_grpc_profile/aio/server/__init__.py
py_grpc_profile/aio/server/interceptor.py
py_grpc_profile/server/__init__.py
py_grpc_profile/server/interceptor.py
py_grpc_profile-0.1.3.dist-info/LICENSE
py_grpc_profile-0.1.3.dist-info/WHEEL
py_grpc_profile-0.1.3.dist-info/METADATA
py_grpc_profile-0.1.3.dist-info/RECORD
